{
  "packet_id": "HO-DET-011-CASE-PACKET-001",
  "packet_type": "platform_case_packet_guardrail",
  "detection_id": "HO-DET-011",
  "proof_ceiling": "CONTROLLED_TEST_VALIDATED",
  "public_safe_status": "NOT_PUBLIC_SAFE",
  "promotion_status": "BLOCKED",
  "validation_result_ref": "hawkinsoperations-validation/reports/ho-det-011/validation-result.json",
  "validation_cases_ref": "hawkinsoperations-validation/validation/successor/ho-det-011/validation-cases.json",
  "validation_pr": "HawkinsOperations/hawkinsoperations-validation#26",
  "validation_merge_commit": "4df879ea7b3c4dc8d564596accc2f66a87ede6a6",
  "validation_status": "pass",
  "controlled_test_validation": true,
  "exact_claim_supported": "HO-DET-011 passed controlled-test validation against controlled Windows service creation fixtures.",
  "runtime_active": false,
  "signal_observed": false,
  "evidence_linked_public_proof": false,
  "public_safe_runtime_proof": false,
  "production_ready": false,
  "fleet_wide": false,
  "live_splunk_fired": false,
  "wazuh_routed": false,
  "cribl_routed": false,
  "aws_live": false,
  "service_creation_coverage_complete": false,
  "ai_decided_disposition": false,
  "ai_may_approve": false,
  "ai_may_promote": false,
  "ai_may_close": false,
  "human_review_required": true,
  "runtime_readiness_truth": {
    "source_truth": "SOURCE_EXISTS",
    "validation_truth": "CONTROLLED_TEST_VALIDATED",
    "platform_truth": "CASE_PACKET_ALIGNED_TO_17_CASE_VALIDATION",
    "proof_truth": "PRIVATE_RUNTIME_EVIDENCE_CAPTURED_NOT_PROMOTED",
    "runtime_truth": "PUBLIC_RUNTIME_BLOCKED",
    "signal_truth": "SIGNAL_NOT_OBSERVED_PUBLIC_OR_ROUTED",
    "evidence_truth": "NO_RAW_PRIVATE_EVIDENCE_IN_PLATFORM_PACKET",
    "ai_triage_truth": "AI_SUPPORT_ONLY_NOT_AUTHORITY",
    "public_proof_truth": "NOT_PUBLIC_SAFE",
    "human_review_truth": "HUMAN_REVIEW_REQUIRED"
  },
  "telemetry_boundary": {
    "event_7045": "Windows System / Service Control Manager service-install telemetry",
    "event_4697": "Windows Security service installation auditing where available",
    "event_1": "Sysmon process creation context where available"
  },
  "validation_counts": {
    "total_cases": 17,
    "positive_cases": 7,
    "negative_cases": 10,
    "pass": 17,
    "fail": 0,
    "matched_positive_count": 7,
    "missed_positive_count": 0,
    "false_positive_negative_count": 0
  },
  "allowed_claims": [
    "HO-DET-011 source artifacts exist in the detections repository.",
    "HO-DET-011 passed controlled-test validation against controlled Windows service creation fixtures.",
    "HO-DET-011 platform case-packet guardrail exists for controlled-test-scope claim boundaries.",
    "HO-DET-011 remains capped at CONTROLLED_TEST_VALIDATED."
  ],
  "blocked_claims": [
    "runtime-active",
    "signal-observed",
    "public-safe",
    "evidence-linked public proof",
    "public-safe runtime proof",
    "Splunk-fired",
    "live Splunk fired",
    "Wazuh-routed",
    "Cribl-routed",
    "Security Onion observed",
    "Suricata observed",
    "Zeek observed",
    "AWS-live",
    "production-ready",
    "production triage",
    "fleet-wide",
    "autonomous SOC",
    "service-creation coverage completeness",
    "attack coverage completeness",
    "AI-decided disposition",
    "AI-approved disposition",
    "analyst-approved disposition",
    "AI-closed disposition"
  ],
  "privacy_boundary": {
    "controlled_test_fixtures_only": true,
    "local_private_paths_included": false,
    "hostnames_included": false,
    "lan_ips_included": false,
    "secret_material_included": false,
    "screenshots_included": false,
    "raw_runtime_evidence_included": false
  },
  "does_not_prove": [
    "runtime activity",
    "signal observation",
    "public-safe evidence",
    "production deployment",
    "fleet-wide coverage",
    "routing through Wazuh or Cribl",
    "AWS-live coverage",
    "complete service-creation coverage"
  ]
}
